ocrstack/__init__.py
ocrstack/config/__init__.py
ocrstack/config/config.py
ocrstack/data/__init__.py
ocrstack/data/collate.py
ocrstack/data/dataset.py
ocrstack/data/vocab.py
ocrstack/engine/__init__.py
ocrstack/engine/checkpoint.py
ocrstack/engine/evaluator.py
ocrstack/engine/logger.py
ocrstack/engine/trainer.py
ocrstack/engine/visualizer.py
ocrstack/loss/__init__.py
ocrstack/loss/label_smooth_loss.py
ocrstack/metrics/__init__.py
ocrstack/metrics/metric.py
ocrstack/metrics/ocr.py
ocrstack/models/__init__.py
ocrstack/models/base.py
ocrstack/models/conv.py
ocrstack/models/conv_attn_rnn.py
ocrstack/models/conv_rnn.py
ocrstack/models/conv_seq2seq.py
ocrstack/models/utils.py
ocrstack/models/layers/__init__.py
ocrstack/models/layers/attention.py
ocrstack/models/layers/collapse.py
ocrstack/models/layers/feature.py
ocrstack/models/layers/global_context.py
ocrstack/models/layers/multihead_attention.py
ocrstack/models/layers/positional_encoding.py
ocrstack/models/layers/sequence_decoder.py
ocrstack/models/layers/sequence_encoder.py
ocrstack/models/layers/string_decoder.py
ocrstack/opts/__init__.py
ocrstack/opts/attention.py
ocrstack/opts/collapse.py
ocrstack/opts/feature.py
ocrstack/opts/global_context.py
ocrstack/opts/multihead_attention.py
ocrstack/opts/positional_encoding.py
ocrstack/opts/sequence_decoder.py
ocrstack/opts/sequence_encoder.py
ocrstack/opts/string_decoder.py
ocrstack/transforms/__init__.py
ocrstack/transforms/image.py
ocrstack/transforms/string.py
ocrstack/utils/__init__.py
ocrstack/utils/config.py
ocrstack-0.0.5.dev113.dist-info/AUTHORS
ocrstack-0.0.5.dev113.dist-info/LICENSE
ocrstack-0.0.5.dev113.dist-info/METADATA
ocrstack-0.0.5.dev113.dist-info/WHEEL
ocrstack-0.0.5.dev113.dist-info/dependency_links.txt
ocrstack-0.0.5.dev113.dist-info/pbr.json
ocrstack-0.0.5.dev113.dist-info/top_level.txt
ocrstack-0.0.5.dev113.dist-info/RECORD
