Metadata-Version: 2.1
Name: ocrstack
Version: 0.0.5.dev113
Summary: A simple OCR package
Home-page: https://github.com/vinhloiit/ocrstack
Author: VinhLoiIT
License: GPLv3
Keywords: pytorch OCR
Platform: UNKNOWN
Classifier: Programming Language :: Python :: 3
Classifier: License :: OSI Approved :: GNU General Public License v3 (GPLv3)
Classifier: Operating System :: OS Independent
Classifier: Topic :: Scientific/Engineering :: Artificial Intelligence
Requires-Python: >=3.7
License-File: LICENSE
License-File: AUTHORS
Requires-Dist: editdistance
Requires-Dist: numpy
Requires-Dist: PyYAML
Requires-Dist: Pillow
